hakka_cli-0.1.3.data/scripts/install.sh
hakkacli/__init__.py
hakkacli/main.py
hakkacli/scripts/__init__.py
hakkacli/scripts/install.sh
hakka_cli-0.1.3.dist-info/METADATA
hakka_cli-0.1.3.dist-info/WHEEL
hakka_cli-0.1.3.dist-info/entry_points.txt
hakka_cli-0.1.3.dist-info/top_level.txt
hakka_cli-0.1.3.dist-info/RECORD
